dwload_server/__init__.py
dwload_server/constants.py
dwload_server/dev_shell.py
dwload_server/dwl2bas.py
dwload_server/exceptions.py
dwload_server/hooks/__init__.py
dwload_server/hooks/dynamic_dwl.py
dwload_server/hooks/read_ascii.py
dwload_server/hooks/save_ascii.py
dwload_server/pyscripts/autoload_dwl.py
dwload_server/server_base.py
dwload_server/server_becker.py
dwload_server/server_serial.py
dwload_server/utils/__init__.py
dwload_server/utils/file_tools.py
dwload_server/utils/hook_handler.py
dwload_server-0.5.1.dist-info/LICENSE
dwload_server-0.5.1.dist-info/METADATA
dwload_server-0.5.1.dist-info/WHEEL
dwload_server-0.5.1.dist-info/entry_points.txt
dwload_server-0.5.1.dist-info/RECORD
