Metadata-Version: 2.1
Name: dwload-server
Version: 0.5.1
Summary: DWLOAD server implemented in Python
Home-page: https://github.com/6809/DwLoadServer
Keywords: DWLOAD,DriveWire,6809,Dragon,CoCo
Author: JensDiemer
Author-email: dwload_server@jensdiemer.de
Requires-Python: >=3.9,<4.0
Classifier: Development Status :: 5 - Production/Stable
Classifier: Environment :: MacOS X
Classifier: Environment :: Other Environment
Classifier: Environment :: Win32 (MS Windows)
Classifier: Environment :: X11 Applications
Classifier: Intended Audience :: Developers
Classifier: Intended Audience :: Education
Classifier: Intended Audience :: End Users/Desktop
Classifier: License :: OSI Approved :: GNU General Public License v3 or later (GPLv3+)
Classifier: Operating System :: OS Independent
Classifier: Programming Language :: Python
Classifier: Programming Language :: Python :: 3
Classifier: Programming Language :: Python :: 3.9
Classifier: Programming Language :: Python :: 3.10
Classifier: Programming Language :: Python :: 3.11
Classifier: Programming Language :: Python :: 3
Requires-Dist: dragonlib
Requires-Dist: pyserial
